hsuhs_vlsi_hw8-9/lab_SVA/enums.sv
enum logic[3:0] {
    IDLE = 0,
    CHECK_CACHE = 1,
    READ_MEM = 2,
    HIT = 3,
    MISS = 4,
    READ_CACHE = 5
  } ps,ns;

hsuhs_vlsi_hw8-9/lab_SVA/property.sv
// s_check: at every posedge of the clock, state CHECK_CACHE is followed by HIT one clock cycle later
  sequence s_check;
    @(posedge tb.clk) (tb.iDUT.ps == CHECK_CACHE) ##1 (tb.iDUT.ps == HIT);
  endsequence
  
// s_read_when_miss: read_memory is only raised in MISS state
  sequence s_read_when_miss;
    @(posedge tb.clk) $rose(tb.read_memory) && (tb.iDUT.ps == MISS);
  endsequence
  
// p_check_impl: at every posedge of the clock, if current state is CHECK_CACHE, then it is followed by either HIT or MISS one to two clock cycles later
  property p_check_impl;
    @(posedge tb.clk) 
    (tb.iDUT.ps == CHECK_CACHE) |-> ##[1:2] (tb.iDUT.ps == HIT || tb.iDUT.ps == MISS);
  endproperty
// This is to be defined as a property, using property...endproperty, not sequence...endsequence

// s_read_mem: every time current state is READ_MEM then read_memory is also asserted  
  sequence s_read_mem;
    @(posedge tb.clk) (tb.iDUT.ps == READ_MEM) ##0 (tb.read_memory == 1);
  endsequence

/*
// make sure the ps is MISS, then check if read_memory is only raised there
  property s_read_miss;
    @(posedge tb.clk) (tb.iDUT.ps == MISS) |-> s_read_when_miss;
    //@(posedge tb.clk) s_read_when_miss |-> (tb.iDUT.ps == MISS);
  endproperty
  */

hsuhs_vlsi_hw8-9/lab_SVA/cache_ctrl.sv
//`include "enums.sv"
//`include "property.sv"

module cache_ctrl(
  // address from which the data is to be read
  input logic [7:0] address,
  // input instructing a read from the cache
  input logic read,
  // input that tells the ctrl whether the data is in cache (1) , memory (2) .
  // if no read is in progress, value is 0
  input logic[1:0] hit_or_miss,
  input bit clk,
  // active high asynchronous reset
  input logic rst,
  // ctrl instructs to read from memory
  output logic read_memory,
  // ctrl instructs to read from cache
  output logic read_cache,
  // an information signal that tells the chip it is checking the cache
  output logic check_cache
);
  
  enum logic[3:0] {
    IDLE = 0,
    CHECK_CACHE = 1,
    READ_MEM = 2,
    HIT = 3,
    MISS = 4,
    READ_CACHE = 5
  } ps,ns;

  
  always_ff @(posedge clk, posedge rst) begin
    if (rst) begin
      ps <= IDLE; 
    end else
      ps <= ns;
  end
  
  always_comb begin
    case (ps)
      IDLE: begin
        ns = read? CHECK_CACHE:IDLE;
        check_cache = 1;
        read_memory = 0;
        read_cache = 0;
      end
      CHECK_CACHE: begin
        check_cache = 0;
        if (hit_or_miss == 0) ns = CHECK_CACHE;
        else if (hit_or_miss == 1) ns = HIT;
        else ns = MISS;
      end
      HIT: begin
        read_cache = 1;
        ns = READ_CACHE;
      end
      MISS: begin
        read_memory = 1;
        ns = READ_MEM;
      end
      READ_CACHE: begin
        ns = IDLE;
        read_cache = 0;
      end
      READ_MEM: begin
        ns = IDLE;
        read_memory = 0;
      end
      
    endcase
    
  end
    
endmodule

hsuhs_vlsi_hw8-9/lab_SVA/tb.sv
`include "property.sv"
`include "enums.sv"

module tb;
  //input
  logic [7:0] address;
  logic read;
  logic[1:0] hit_or_miss;
  bit clk;
  logic rst;
  
  //output
  logic read_memory;
  logic read_cache;
  logic check_cache;  
  
  parameter CYCLE = 10;
  
  cache_ctrl iDUT(.*);
  
  
  // Declare the property
  ap_1: assert property(s_check)
    $display ("Assertion: s_check pass!");
    else $display ("Assertion: s_check fail!");
  cp_1: cover property(s_check)
    $display ("Cover: s_check pass!");
    
  ap_2: assert property(s_read_when_miss)
    $display ("Assertion: s_read_when_miss pass!");
    else $display ("Assertion: s_read_when_miss fail!");
  cp_2: cover property(s_read_when_miss)
    $display ("Cover: s_read_when_miss pass!");
        
  ap_3: assert property(p_check_impl)
    $display ("Assertion: p_check_impl pass!");
    else $display ("Assertion: p_check_impl fail!");
  cp_3: cover property(p_check_impl)
    $display ("Cover: p_check_impl pass!");
    
  ap_4: assert property(s_read_mem)
    $display ("Assertion: s_read_mem pass!");
    else $display ("Assertion: s_read_mem fail!");
  cp_4: cover property(s_read_mem)
    $display ("Cover: s_read_mem pass!");
  
  
  initial begin
    read = 0;
    rst = 1;
    address = 'b0;
    hit_or_miss = 'b0;
    $display("==========================================================");
    $display("Scenario 1 Starts ... ");
    $display("Trace: IDLE => CHECK_CACHE => HIT => READ_CACHE => IDLE");
    $display("==========================================================");
    
    #(CYCLE) rst = 0;
    
    #(CYCLE) read = 1; // ns = CHECK_CACHE
    
    #(CYCLE) read = 0;
    hit_or_miss = 1; // 1 cycle later, ns = HIT
    read = 0;
    
    #(CYCLE*2) hit_or_miss = 0; // 2 cycle later, back to IDLE
    
    $display("==========================================================");
    $display("Scenario 1 Ends ... ");
    $display("==========================================================");
    
    #(CYCLE)
    
    $display("==========================================================");
    $display("Scenario 2 Starts ... ");
    $display("Trace: IDLE => CHECK_CACHE*2 => MISS => READ_MEM => IDLE");
    $display("==========================================================");
    
    #(CYCLE) read = 1; // ns = CHECK_CACHE
    #(CYCLE) read = 0;
    #(CYCLE) hit_or_miss = 2; // 2 cycle later, ns = MISS
    
    #(CYCLE*2) hit_or_miss = 0; // 2 cycle later, back to IDLE
       
    $display("==========================================================");
    $display("Scenario 2 Ends ... ");
    $display("==========================================================");
    
    #(CYCLE)
    
    $display("==========================================================");
    $display("Scenario 3 Starts ... ");
    $display("Violate all assertions ...  ");
    $display("Trace: IDLE => CHECK_CACHE*4 => rst asserted => IDLE");
    $display("==========================================================");
    
    #(CYCLE) read = 1; // ns = CHECK_CACHE
    #(CYCLE) read = 0;
    hit_or_miss = 0; 
    #(CYCLE*3) // // stay in CHECK_CACHE for 4 clock cycles
    
    rst = 1; // ns will be back to IDLE
    #(CYCLE*2)
    rst = 0;
    
    #(CYCLE*2)
    
    $display("==========================================================");
    $display("Scenario 3 Ends ... ");
    $display("==========================================================");
    
    
    $dumpflush;    
    $stop;
  end
    
  // Display the output at every clock cycle
  initial begin
    #5
    $display("[%0t] check_cahce = %d, read_memory = %d, read_cache = %d", $time, check_cache, read_memory, read_cache);
    
    forever #(CYCLE) $display("[%0t] check_cahce = %d, read_memory = %d, read_cache = %d", $time, check_cache, read_memory, read_cache);
  end
  
  initial begin
    $dumpfile("test.vcd");
    $dumpvars(1, tb);
  end
  
  //clock cycle generation
  initial begin
    clk = 0; 
    forever #(CYCLE/2) clk = ~clk;
  end
endmodule

hsuhs_vlsi_hw8-9/lab_SVA/test.vcd
$date
	Wed Jun  1 19:04:49 2022
$end
$version
	ModelSim Version 2021.2
$end
$timescale
	1ns
$end

$scope module tb $end
$var parameter 32 ! CYCLE $end
$var reg 8 " address [7:0] $end
$var reg 1 # read $end
$var reg 2 $ hit_or_miss [1:0] $end
$var reg 1 % clk $end
$var reg 1 & rst $end
$var reg 1 ' read_memory $end
$var reg 1 ( read_cache $end
$var reg 1 ) check_cache $end

$scope begin ap_1 $end
$upscope $end

$scope begin cp_1 $end
$upscope $end

$scope begin ap_2 $end
$upscope $end

$scope begin cp_2 $end
$upscope $end

$scope begin ap_3 $end
$upscope $end

$scope begin cp_3 $end
$upscope $end

$scope begin ap_4 $end
$upscope $end

$scope begin cp_4 $end
$upscope $end
$upscope $end
$enddefinitions $end
#0
$dumpvars
b0 "
0#
b0 $
0%
1&
0'
0(
1)
b1010 !
$end
#5
1%
#10
0&
0%
#15
1%
#20
1#
0%
#25
1%
0)
#30
0#
b1 $
0%
#35
1%
1(
#40
0%
#45
1%
0(
#50
b0 $
0%
#55
1%
1)
#60
0%
#65
1%
#70
1#
0%
#75
1%
0)
#80
0#
0%
#85
1%
#90
b10 $
0%
#95
1%
1'
#100
0%
#105
1%
0'
#110
b0 $
0%
#115
1%
1)
#120
0%
#125
1%
#130
1#
0%
#135
1%
0)
#140
0#
0%
#145
1%
#150
0%
#155
1%
#160
0%
#165
1%
#170
1&
0%
1)
#175
1%
#180
0%
#185
1%
#190
0&
0%
