hsuhs_vlsi_hw5/rtl_src/count.sv
// Code your design here
module count #(parameter W = 8) (
  input [W-1:0] a_in,
  input [1:0] sel,
  input clk,
  input start,
  input rst,
  output logic done,
  output logic [W-1:0] cntout
);
  
  // Define enumerated types and vectors for present state and next state
  enum logic [1:0] {
    IDLE = 2'b00,
    BUSY = 2'b01,
    DONE = 2'b10
  } count_ps, count_ns;
  
  logic [W-1:0] countZero; // Initialize
  logic [W-1:0] countOne; // Initialize
  
  logic [W-1:0] finCount0;
  logic [W-1:0] finCount1;
  
  // Infer the count_ps vector flip-flops
  // rst is asynchronous active high reset
  always_ff @(posedge clk, posedge rst) begin
    if (rst) count_ps <= IDLE;
    else     count_ps <= count_ns;
  end

  
  logic startToCount; // State Machine output (trigger)
  logic stopToCount; // stop to count and force the next state to be DONE
  logic [W:0] a_reg; // Store a_in value in temporary register [W:1]
  
  //////////////////
  // STATE MACHINE//
  //////////////////
  
  always_comb begin
    
    // ONLY 3 states: IDLE, BUSY, DONE
    unique case (count_ps)      
      IDLE: begin
        
        // start to count and tell a_reg to shift
        if (start) begin 
          count_ns = BUSY;
          {done, startToCount} = 2'b0_1;
        end
        
        else begin
          count_ns = IDLE;
          {done, startToCount} = 2'b0_0;
        end        
      end
      
      BUSY: begin
        
        // stop to count and the cntout will be available
        if (stopToCount) begin
          count_ns = DONE;
          {done, startToCount} = 2'b1_0; 
        end
        
        // keep counting and shifting
        else begin
          count_ns = BUSY;
          {done, startToCount} = 2'b0_0;
        end
      end
      
      // Next state will "always" be IDLE
      DONE: begin
        count_ns = IDLE;
        {done, startToCount} = 2'b0_0;
      end            
    endcase  
  end
  
  //////////////
  // DATA PATH//
  //////////////
  
  
  // Store a_in into the register if startToCount asserts
  // Set a_reg[0] = 1 and the rest of the bits is a_in 
  // Shift left if it is in the BUSY state and haven't done yet 
  always @(posedge clk) begin
    if (count_ps == IDLE) a_reg <= {a_in, 1'b1};
    if (count_ns == BUSY && !done) a_reg <= (a_reg << 1); 
  end
  

  
  // Count 0's and 1's
  always_ff @(posedge clk) begin
    if (rst) begin
      countZero <= 'b0;
      countOne <= 'b0;
    end
    
    // Counting function is only needed if next state is BUSY and not done yet
    else if (count_ns == BUSY && !done) begin       
      if (a_reg[W] == 1'b0) countZero <= countZero + 1'b1; //MSB = 0
      else if (a_reg[W] == 1'b1)   countOne <= countOne + 1'b1; // MSB = 1
      else begin
        // MSB detect 'x or z' and force result to be 'x'
        countZero <= countZero + 1'bx;
        countOne <= countOne + 1'bx;
      end
    end
    
    // reset the counter to '0' if present state is DONE
    else /*if (count_ps == IDLE)*/ {countOne, countZero} <= 'b0;
  end
  
  // Trigger the stopToCount signal
  always @(posedge clk) begin
    if (count_ns == BUSY) begin
      if (a_reg[W-2:0] == 'b0) stopToCount = 'b1; // to stop counting and telling FSM
    end  
    else stopToCount = 'b0; // still need to count and shift left
    
    
  end
  

  // Store the final value
  always_comb begin
    if (rst) begin
      finCount0 = 'b0;
      finCount1 = 'b0;
    end
    else if (count_ns == DONE) begin
      finCount0 = countZero;
      finCount1 = countOne;
    end    
    else begin
      finCount0 = 'b0; // reset to 0
      finCount1 = 'b0; // reset to 0
    end
    
  end
  
  // 1-hot encoding
  always_comb begin    
    if (count_ns == DONE) begin
      unique case (1'b1)
        
        // counting '0'
        sel[0]: begin
          cntout = finCount0;
        end
        
        // counting '1'
        sel[1]: begin
          cntout = finCount1;
        end
      endcase
    end
    
  else cntout = 'b0; // reset to 0
  end
  
endmodule

hsuhs_vlsi_hw5/tb.sv
// Code your testbench here
`timescale 1ns/1ns

module tb_count();

parameter W = 8;

reg [W-1:0] a_in;
reg [1:0] sel;
reg clk;
reg start;
reg rst;
wire done;
wire [W-1:0] cntout;  


count #(.W(W)) COUNT(.*);


initial begin

  // start from IDLE
  clk = 1;
  rst = 1;
  start = 0;

  # 14 rst = 0;

  /////////////////////
  //correct cntout: 3//
  /////////////////////
  
  # 6 a_in = 8'b0000_1011; // count this
  start = 1;
  sel = 2'b10; // count 1
  # 10 start = 0;
  
  a_in = 8'b1111_1111; // this will not be counted
  # 100
  
  
  /////////////////////
  //correct cntout: 6//
  /////////////////////

  a_in = 8'b1101_1111; // this will not be counted

  # 10 a_in = 8'b0100_0010; // count this
  start = 1;
  
  // test that cntout will not be 'x'
  # 10 a_in = 8'bxxxx_xxxx; // this will not be counted
  sel = 2'b01; // count 0
  start = 0;
  
  # 40
  a_in = 8'b1010_x001; // this will be used in 'next' block
  # 80
  
  /////////////////////
  //correct cntout: x//
  /////////////////////
  
  // a_in is 8'b1010_x001 here!!
  start = 1;
  # 10 start = 0;
  # 30 sel = 2'b10; // count 1, but x is one of the bit
  # 70
    
  # 30 $dumpflush;
  $stop;


end

initial begin
$dumpfile("test.vcd");
$dumpvars(1, tb_count);

end

// one clock cycle is 10ns
always
  #5 clk = ~clk;

endmodule

hsuhs_vlsi_hw5/test.vcd
$date
	Thu May 12 21:53:55 2022
$end
$version
	ModelSim Version 2021.2
$end
$timescale
	1ps
$end

$scope module tb_count $end
$var parameter 32 ! W $end
$var reg 8 " a_in [7:0] $end
$var reg 2 # sel [1:0] $end
$var reg 1 $ clk $end
$var reg 1 % start $end
$var reg 1 & rst $end
$var wire 1 ' done $end
$var wire 1 ( cntout [7] $end
$var wire 1 ) cntout [6] $end
$var wire 1 * cntout [5] $end
$var wire 1 + cntout [4] $end
$var wire 1 , cntout [3] $end
$var wire 1 - cntout [2] $end
$var wire 1 . cntout [1] $end
$var wire 1 / cntout [0] $end
$upscope $end
$enddefinitions $end
#0
$dumpvars
bx "
bx #
1$
0%
1&
b1000 !
x'
x/
x.
x-
x,
x+
x*
x)
x(
$end
#157
0(
0)
0*
0+
0,
0-
0.
0/
#254
0'
#5000
0$
#10000
1$
#14000
0&
#15000
0$
#20000
b1011 "
1%
b10 #
1$
#25000
0$
#30000
0%
b11111111 "
1$
#35000
0$
#40000
1$
#45000
0$
#50000
1$
#55000
0$
#60000
1$
#65000
0$
#70000
1$
#75000
0$
#80000
1$
#85000
0$
#90000
1$
#95000
0$
#100000
1$
#100146
1'
#100304
x(
x)
x*
x+
x,
x-
x.
x/
#105000
0$
#110000
1$
#110154
0'
#110310
0(
0)
0*
0+
0,
0-
0.
0/
#115000
0$
#120000
1$
#125000
0$
#130000
b11011111 "
1$
#135000
0$
#140000
b1000010 "
1%
1$
#145000
0$
#150000
bx "
b1 #
0%
1$
#155000
0$
#160000
1$
#165000
0$
#170000
1$
#175000
0$
#180000
1$
#185000
0$
#190000
b1010x001 "
1$
#195000
0$
#200000
1$
#205000
0$
#210000
1$
#215000
0$
#220000
1$
#220146
1'
#220284
x(
x)
x*
x+
x,
x-
x.
x/
#225000
0$
#230000
1$
#230154
0'
#230291
0(
0)
0*
0+
0,
0-
0.
0/
#235000
0$
#240000
1$
#245000
0$
#250000
1$
#255000
0$
#260000
1$
#265000
0$
#270000
1%
1$
#275000
0$
#280000
0%
1$
#285000
0$
#290000
1$
#295000
0$
#300000
1$
#305000
0$
#310000
b10 #
1$
#315000
0$
#320000
1$
#325000
0$
#330000
1$
#335000
0$
#340000
1$
#345000
0$
#350000
1$
#350146
1'
#350304
x(
x)
x*
x+
x,
x-
x.
x/
#355000
0$
#360000
1$
#360154
0'
#360310
0(
0)
0*
0+
0,
0-
0.
0/
